jnt_admin_tools/__init__.py
jnt_admin_tools/admin/__init__.py
jnt_admin_tools/admin/base_admin.py
jnt_admin_tools/admin/base_admin_tools.py
jnt_admin_tools/admin/base_changeform_submit.py
jnt_admin_tools/admin/mixins/__init__.py
jnt_admin_tools/admin/mixins/admin_tools.py
jnt_admin_tools/admin/mixins/changeform_submits.py
jnt_admin_tools/apps.py
jnt_admin_tools/checks.py
jnt_admin_tools/dashboard/__init__.py
jnt_admin_tools/dashboard/apps.py
jnt_admin_tools/dashboard/dashboards.py
jnt_admin_tools/dashboard/forms.py
jnt_admin_tools/dashboard/management/__init__.py
jnt_admin_tools/dashboard/management/commands/__init__.py
jnt_admin_tools/dashboard/management/commands/clear_dashboard_preferences.py
jnt_admin_tools/dashboard/management/commands/customdashboard.py
jnt_admin_tools/dashboard/migrations/0001_initial.py
jnt_admin_tools/dashboard/migrations/__init__.py
jnt_admin_tools/dashboard/models.py
jnt_admin_tools/dashboard/modules.py
jnt_admin_tools/dashboard/registry.py
jnt_admin_tools/dashboard/static/jnt_admin_tools/css/dashboard.css
jnt_admin_tools/dashboard/static/jnt_admin_tools/css/jquery/images/animated-overlay.gif
jnt_admin_tools/dashboard/static/jnt_admin_tools/css/jquery/images/ui-bg_flat_0_aaaaaa_40x100.png
jnt_admin_tools/dashboard/static/jnt_admin_tools/css/jquery/images/ui-bg_flat_75_ffffff_40x100.png
jnt_admin_tools/dashboard/static/jnt_admin_tools/css/jquery/images/ui-bg_glass_55_fbf9ee_1x400.png
jnt_admin_tools/dashboard/static/jnt_admin_tools/css/jquery/images/ui-bg_glass_65_ffffff_1x400.png
jnt_admin_tools/dashboard/static/jnt_admin_tools/css/jquery/images/ui-bg_glass_75_dadada_1x400.png
jnt_admin_tools/dashboard/static/jnt_admin_tools/css/jquery/images/ui-bg_glass_75_e6e6e6_1x400.png
jnt_admin_tools/dashboard/static/jnt_admin_tools/css/jquery/images/ui-bg_glass_95_fef1ec_1x400.png
jnt_admin_tools/dashboard/static/jnt_admin_tools/css/jquery/images/ui-bg_highlight-soft_75_cccccc_1x100.png
jnt_django_admin_tools-0.14.3.dist-info/METADATA
jnt_django_admin_tools-0.14.3.dist-info/WHEEL
jnt_django_admin_tools-0.14.3.dist-info/RECORD
