Metadata-Version: 2.3
Name: jnt-django-admin-tools
Version: 0.14.3
Summary: Improved django admin interface
Author: Junte
Author-email: tech@junte.ru
Requires-Python: >=3.11,<4.0
Classifier: Environment :: Web Environment
Classifier: Intended Audience :: Developers
Classifier: License :: OSI Approved :: MIT License
Classifier: Operating System :: OS Independent
Classifier: Programming Language :: Python :: 3
Classifier: Programming Language :: Python :: 3.11
Classifier: Programming Language :: Python :: 3.12
Classifier: Programming Language :: Python :: 3.13
Classifier: Topic :: Software Development :: Libraries :: Python Modules
Requires-Dist: django (>=4)
Requires-Dist: jnt-django-toolbox
